discord_orchestrator/__init__.py
discord_orchestrator/client.py
discord_orchestrator/config.py
discord_orchestrator/constants.py
discord_orchestrator/exceptions.py
discord_orchestrator/realtime.py
discord_orchestrator/models/__init__.py
discord_orchestrator/models/bot.py
discord_orchestrator/models/command.py
discord_orchestrator/models/event.py
discord_orchestrator/models/metrics.py
discord_orchestrator/models/responses.py
discord_orchestrator/models/webhook.py
discord_orchestrator/resources/__init__.py
discord_orchestrator/resources/base.py
discord_orchestrator/resources/base_instance.py
discord_orchestrator/resources/bot_instance.py
discord_orchestrator/resources/bots.py
discord_orchestrator/resources/commands.py
discord_orchestrator/resources/health.py
discord_orchestrator/resources/interactions.py
discord_orchestrator/resources/metrics.py
discord_orchestrator/resources/slash_commands.py
discord_orchestrator/resources/webhooks.py
discord_orchestrator/resources/bot_mixins/__init__.py
discord_orchestrator/resources/bot_mixins/channels.py
discord_orchestrator/resources/bot_mixins/direct_messages.py
discord_orchestrator/resources/bot_mixins/messaging.py
discord_orchestrator/resources/bot_mixins/moderation.py
discord_orchestrator/resources/bot_mixins/server.py
discord_orchestrator/resources/bot_mixins/users.py
discord_orchestrator/utils/__init__.py
discord_orchestrator/utils/http.py
discord_orchestrator/utils/pagination.py
discord_orchestrator/utils/payload.py
discord_orchestrator/utils/validation.py
discord_orchestrator/utils/webhook.py
discord_orchestrator_sdk-0.1.8.dist-info/METADATA
discord_orchestrator_sdk-0.1.8.dist-info/WHEEL
discord_orchestrator_sdk-0.1.8.dist-info/RECORD
