Metadata-Version: 2.4
Name: discord-orchestrator-sdk
Version: 0.1.8
Summary: Python SDK for Discord Bot Orchestrator
Project-URL: Documentation, https://github.com/your-org/discord-bot-orchestrator#readme
Project-URL: Issues, https://github.com/your-org/discord-bot-orchestrator/issues
Project-URL: Source, https://github.com/your-org/discord-bot-orchestrator
Author: Discord Bot Orchestrator Team
License-Expression: MIT
Keywords: automation,bot,discord,orchestrator,sdk
Classifier: Development Status :: 4 - Beta
Classifier: Intended Audience :: Developers
Classifier: License :: OSI Approved :: MIT License
Classifier: Programming Language :: Python :: 3
Classifier: Programming Language :: Python :: 3.10
Classifier: Programming Language :: Python :: 3.11
Classifier: Programming Language :: Python :: 3.12
Classifier: Topic :: Communications :: Chat
Classifier: Topic :: Software Development :: Libraries :: Python Modules
Classifier: Typing :: Typed
Requires-Python: >=3.10
Requires-Dist: pydantic>=2.0.0
Requires-Dist: python-socketio[client]>=5.0.0
Requires-Dist: requests>=2.28.0
Provides-Extra: dev
Requires-Dist: black>=23.0.0; extra == 'dev'
Requires-Dist: mypy>=1.0.0; extra == 'dev'
Requires-Dist: pytest-cov>=4.0.0; extra == 'dev'
Requires-Dist: pytest>=7.0.0; extra == 'dev'
Requires-Dist: responses>=0.23.0; extra == 'dev'
Requires-Dist: ruff>=0.1.0; extra == 'dev'
Requires-Dist: types-requests>=2.28.0; extra == 'dev'
